hydrant/__init__.py
hydrant/cli.py
hydrant-0.3.0.dist-info/top_level.txt
hydrant-0.3.0.dist-info/entry_points.txt
hydrant-0.3.0.dist-info/METADATA
hydrant-0.3.0.dist-info/DESCRIPTION.rst
hydrant-0.3.0.dist-info/metadata.json
hydrant-0.3.0.dist-info/WHEEL
hydrant-0.3.0.dist-info/RECORD
