Metadata-Version: 2.0
Name: hydrant
Version: 0.3.0
Summary: Redirects stdin to Amazon Kinesis Firehose.
Home-page: https://github.com/bwbaugh/hydrant
Author: Wesley Baugh
Author-email: wesley@bwbaugh.com
License: BSD
Platform: UNKNOWN
Classifier: Development Status :: 3 - Alpha
Classifier: Environment :: Console
Classifier: Intended Audience :: Developers
Classifier: Programming Language :: Python
Classifier: Programming Language :: Python :: 2
Classifier: Programming Language :: Python :: 2.7
Classifier: Topic :: Utilities
Requires-Dist: botocore (>=1.2.9)
Requires-Dist: click
